{"dependencies":[{"name":"C:\\Users\\pedoe\\Documents\\code\\REU\\yololite-web\\node_modules\\babel-register\\package.json","includedInParent":true,"mtime":1502898848000},{"name":"C:\\Users\\pedoe\\Documents\\code\\REU\\yololite-web\\package.json","includedInParent":true,"mtime":1530210179496},{"name":"C:\\Users\\pedoe\\Documents\\code\\REU\\yololite-web\\.babelrc","includedInParent":true,"mtime":1530215018462}],"generated":{"js":"\"use strict\";\n\nexports.__esModule = true;\n\nexports.default = function () {};\n\nmodule.exports = exports[\"default\"];","map":{"mappings":[{"source":"..\\node_modules\\babel-register\\lib\\browser.js","original":{"line":1,"column":0},"generated":{"line":1,"column":0}},{"source":"..\\node_modules\\babel-register\\lib\\browser.js","original":{"line":2,"column":0},"generated":{"line":2,"column":0}},{"source":"..\\node_modules\\babel-register\\lib\\browser.js","original":{"line":3,"column":0},"generated":{"line":3,"column":0}},{"source":"..\\node_modules\\babel-register\\lib\\browser.js","original":{"line":4,"column":0},"generated":{"line":4,"column":0}},{"source":"..\\node_modules\\babel-register\\lib\\browser.js","original":{"line":5,"column":0},"generated":{"line":5,"column":0}},{"source":"..\\node_modules\\babel-register\\lib\\browser.js","original":{"line":6,"column":0},"generated":{"line":6,"column":0}},{"source":"..\\node_modules\\babel-register\\lib\\browser.js","original":{"line":7,"column":0},"generated":{"line":7,"column":0}}],"sources":{"..\\node_modules\\babel-register\\lib\\browser.js":"\"use strict\";\n\nexports.__esModule = true;\n\nexports.default = function () {};\n\nmodule.exports = exports[\"default\"];"},"lineCount":7}},"hash":"4dc02b9bdaa08dfc6f45ec1171b8b1e7","cacheData":{"env":{}},"id":212}